honeywell_hpma115s0/__init__.py
honeywell_hpma115s0/honeywell_hpma115s0.py
honeywell_hpma115s0-0.0.3.dist-info/LICENSE
honeywell_hpma115s0-0.0.3.dist-info/METADATA
honeywell_hpma115s0-0.0.3.dist-info/WHEEL
honeywell_hpma115s0-0.0.3.dist-info/top_level.txt
honeywell_hpma115s0-0.0.3.dist-info/RECORD
