Metadata-Version: 2.1
Name: honeywell-hpma115s0
Version: 0.0.3
Summary: An interface for honeywell HPMA115S0 particulate matter sensors
Home-page: https://github.com/FEEprojects/honeywell-hpma115s0
Author: Florentin Bulot
Author-email: f.bulot@soton.ac.uk
License: UNKNOWN
Platform: UNKNOWN
Classifier: Programming Language :: Python :: 3
Classifier: License :: OSI Approved :: MIT License
Classifier: Operating System :: OS Independent
Requires-Python: >=3.3, <4
Requires-Dist: pyserial
